pynrpe/__init__.py
pynrpe/site.py
pynrpe-0.1.1.dist-info/METADATA
pynrpe-0.1.1.dist-info/WHEEL
pynrpe-0.1.1.dist-info/entry_points.txt
pynrpe-0.1.1.dist-info/top_level.txt
pynrpe-0.1.1.dist-info/RECORD
