Metadata-Version: 2.1
Name: pynrpe
Version: 0.1.1
Summary: NRPE Checks writen in python
Home-page: https://github.com/tmb28054/pynrpe
Author: Topaz Bott
Author-email: topaz@topazhome.net
License: Apache License 2.0
Classifier: Development Status :: 5 - Production/Stable
Classifier: Natural Language :: English
Classifier: Programming Language :: Python
Classifier: Programming Language :: Python :: 3.8
Classifier: Programming Language :: Python :: 3.9
Classifier: Programming Language :: Python :: 3.10
Classifier: Programming Language :: Python :: 3.11
Classifier: Programming Language :: Python :: 3.12
Classifier: Programming Language :: Python :: 3.13
Requires-Dist: requests
